LICENSE
MANIFEST.in
README.md
setup.cfg
setup.py
lamper/__init__.py
lamper/config.py
lamper/core.py
lamper/decorators.py
lamper/exceptions.py
lamper/https.py
lamper.egg-info/PKG-INFO
lamper.egg-info/SOURCES.txt
lamper.egg-info/dependency_links.txt
lamper.egg-info/requires.txt
lamper.egg-info/top_level.txt