Metadata-Version: 2.1
Name: lamper
Version: 0.1.3
Summary: Lambda Helper for AWS Lambda Api Gateway Integrations
Home-page: https://github.com/epopeia/lamper
Author: Willian Vieira
Author-email: willianvieirarosa@gmail.com
License: MIT
Platform: UNKNOWN
Classifier: License :: OSI Approved :: MIT License
Classifier: Programming Language :: Python
Classifier: Programming Language :: Python :: 3
Classifier: Programming Language :: Python :: 3.6
Classifier: Programming Language :: Python :: Implementation :: CPython
Classifier: Programming Language :: Python :: Implementation :: PyPy
Requires-Python: >=3.6.0
Provides-Extra: tests
